{
  "main": {
    "id": "ed4d8c9d622e2ec6",
    "type": "split",
    "children": [
      {
        "id": "b1319725b19f36c6",
        "type": "tabs",
        "children": [
          {
            "id": "2b7a352f707fd0d2",
            "type": "leaf",
            "pinned": true,
            "state": {
              "type": "markdown",
              "state": {
                "file": "Backlog_1223.md",
                "mode": "source",
                "backlinks": false,
                "source": false
              },
              "pinned": true
            }
          }
        ]
      }
    ],
    "direction": "vertical"
  },
  "left": {
    "id": "d5ba5a98c2bb3d29",
    "type": "split",
    "children": [
      {
        "id": "1507426d5ca80a4f",
        "type": "tabs",
        "children": [
          {
            "id": "e1cb03b33a7d44c5",
            "type": "leaf",
            "state": {
              "type": "file-explorer",
              "state": {
                "sortOrder": "alphabetical"
              }
            }
          },
          {
            "id": "b4cd28172551165a",
            "type": "leaf",
            "state": {
              "type": "search",
              "state": {
                "query": "tag:#NWT",
                "matchingCase": false,
                "explainSearch": false,
                "collapseAll": true,
                "extraContext": false,
                "sortOrder": "alphabetical"
              }
            }
          },
          {
            "id": "51eb5d88f0e28310",
            "type": "leaf",
            "state": {
              "type": "bookmarks",
              "state": {}
            }
          }
        ]
      }
    ],
    "direction": "horizontal",
    "width": 200,
    "collapsed": true
  },
  "right": {
    "id": "dace42f5e87bd3de",
    "type": "split",
    "children": [
      {
        "id": "6d5b491dd8a59fb0",
        "type": "tabs",
        "children": [
          {
            "id": "6e56b5e3b8c63432",
            "type": "leaf",
            "state": {
              "type": "tag",
              "state": {
                "sortOrder": "frequency",
                "useHierarchy": true
              }
            }
          },
          {
            "id": "ba8fbc41910eba6c",
            "type": "leaf",
            "state": {
              "type": "outline",
              "state": {
                "file": "Backlog_1223.md"
              }
            }
          },
          {
            "id": "592b6cb07908dda2",
            "type": "leaf",
            "state": {
              "type": "advanced-tables-toolbar",
              "state": {}
            }
          },
          {
            "id": "70c8e5a78cbd40aa",
            "type": "leaf",
            "state": {
              "type": "file-properties",
              "state": {
                "file": "Backlog_1223.md"
              }
            }
          },
          {
            "id": "38083c4526031a57",
            "type": "leaf",
            "state": {
              "type": "git-view",
              "state": {}
            }
          },
          {
            "id": "9dda15e13ebb299d",
            "type": "leaf",
            "state": {
              "type": "git-history-view",
              "state": {}
            }
          },
          {
            "id": "1dd79e333d1e5d5f",
            "type": "leaf",
            "state": {
              "type": "backlink",
              "state": {
                "file": "Backlog_1223.md",
                "collapseAll": false,
                "extraContext": false,
                "sortOrder": "alphabetical",
                "showSearch": false,
                "searchQuery": "",
                "backlinkCollapsed": false,
                "unlinkedCollapsed": true
              }
            }
          },
          {
            "id": "da4bdcc3d55aa1b3",
            "type": "leaf",
            "state": {
              "type": "outgoing-link",
              "state": {
                "file": "Backlog_1223.md",
                "linksCollapsed": false,
                "unlinkedCollapsed": true
              }
            }
          },
          {
            "id": "0626231ed4acaa99",
            "type": "leaf",
            "state": {
              "type": "all-properties",
              "state": {
                "sortOrder": "frequency"
              }
            }
          }
        ],
        "currentTab": 4
      }
    ],
    "direction": "horizontal",
    "width": 200
  },
  "left-ribbon": {
    "hiddenItems": {
      "switcher:Open quick switcher": false,
      "graph:Open graph view": false,
      "canvas:Create new canvas": false,
      "daily-notes:Open today's daily note": true,
      "templates:Insert template": false,
      "command-palette:Open command palette": true,
      "audio-recorder:Start/stop recording": false,
      "obsidian-excalidraw-plugin:Create new drawing": true,
      "table-editor-obsidian:Advanced Tables Toolbar": false,
      "markdown-importer:Open format converter": false
    }
  },
  "active": "2b7a352f707fd0d2",
  "lastOpenFiles": [
    "NW/SchrödingerGleichung.pdf",
    "NW/~$ysikHA4_2.docx",
    "NW/~$ysikHA4_3.docx",
    "INSY/~$thon-DB-Projektangabe.docx",
    "MEDT/4xHITS-MEDT-Nodejs-Exoplanets/node_modules/sqlstring/lib/SqlString.js",
    "MEDT/4xHITS-MEDT-Nodejs-Exoplanets/node_modules/sqlstring/lib",
    "MEDT/4xHITS-MEDT-Nodejs-Exoplanets/node_modules/mysql2/node_modules/iconv-lite/encodings/tables/shiftjis.json",
    "MEDT/4xHITS-MEDT-Nodejs-Exoplanets/node_modules/mysql2/node_modules/iconv-lite/encodings/tables/gbk-added.json",
    "MEDT/4xHITS-MEDT-Nodejs-Exoplanets/node_modules/mysql2/node_modules/iconv-lite/encodings/tables/gb18030-ranges.json",
    "MEDT/4xHITS-MEDT-Nodejs-Exoplanets/node_modules/mysql2/node_modules/iconv-lite/encodings/tables/cp950.json",
    "MEDT/4xHITS-MEDT-Nodejs-Exoplanets/node_modules/mysql2/node_modules/iconv-lite/encodings/tables/eucjp.json",
    "MEDT/4xHITS-MEDT-Nodejs-Exoplanets/node_modules/mysql2/node_modules/lru-cache/README.md",
    "MEDT/4xHITS-MEDT-Nodejs-Exoplanets/node_modules/mysql2/lib/auth_plugins/caching_sha2_password.md",
    "MEDT/4xHITS-MEDT-Nodejs-Exoplanets/node_modules/long/README.md",
    "MEDT/4xHITS-MEDT-Nodejs-Exoplanets/node_modules/wrap-ansi-cjs/node_modules/strip-ansi/readme.md",
    "MEDT/4xHITS-MEDT-Nodejs-Exoplanets/node_modules/wrap-ansi-cjs/node_modules/string-width/readme.md",
    "MEDT/4xHITS-MEDT-Nodejs-Exoplanets/node_modules/wrap-ansi-cjs/node_modules/emoji-regex/README.md",
    "MEDT/4xHITS-MEDT-Nodejs-Exoplanets/node_modules/wrap-ansi-cjs/node_modules/ansi-styles/readme.md",
    "MEDT/4xHITS-MEDT-Nodejs-Exoplanets/node_modules/wrap-ansi-cjs/node_modules/ansi-regex/readme.md",
    "MEDT/4xHITS-MEDT-Nodejs-Exoplanets/node_modules/strip-ansi-cjs/node_modules/ansi-regex/readme.md",
    "MEDT/4xHITS-MEDT-Nodejs-Exoplanets/node_modules/string-width-cjs/node_modules/strip-ansi/readme.md",
    "MEDT/4xHITS-MEDT-Nodejs-Exoplanets/node_modules/string-width-cjs/node_modules/emoji-regex/README.md",
    "MEDT/4xHITS-MEDT-Nodejs-Exoplanets/node_modules/string-width-cjs/node_modules/ansi-regex/readme.md",
    "MEDT/4xHITS-MEDT-Nodejs-Exoplanets/node_modules/send/node_modules/ms/readme.md",
    "MEDT/4xHITS-MEDT-Nodejs-Exoplanets/node_modules/send/node_modules/ms/license.md",
    "MEDT/4xHITS-MEDT-Nodejs-Exoplanets/node_modules/difunc/coverage/lcov-report/sort-arrow-sprite.png",
    "MEDT/4xHITS-MEDT-Nodejs-Exoplanets/node_modules/ts-log/example/screenshot.jpg",
    "MEDT/4xHITS-MEDT-Nodejs-Exoplanets/node_modules/@pkgjs/parseargs/README.md",
    "MEDT/4xHITS-MEDT-Nodejs-Exoplanets/node_modules/@pkgjs/parseargs/CHANGELOG.md",
    "MEDT/4xHITS-MEDT-Nodejs-Exoplanets/node_modules/@isaacs/cliui/README.md",
    "MEDT/4xHITS-MEDT-Nodejs-Exoplanets/node_modules/wrap-ansi-cjs/readme.md",
    "MEDT/4xHITS-MEDT-Nodejs-Exoplanets/node_modules/wrap-ansi/readme.md",
    "MEDT/4xHITS-MEDT-Nodejs-Exoplanets/node_modules/utils-merge/README.md",
    "MEDT/4xHITS-MEDT-Nodejs-Exoplanets/node_modules/vary/README.md",
    "MEDT/4xHITS-MEDT-Nodejs-Exoplanets/node_modules/vary/HISTORY.md",
    "MEDT/4xHITS-MEDT-Nodejs-Exoplanets/node_modules/which/README.md",
    "MEDT/4xHITS-MEDT-Nodejs-Exoplanets/node_modules/which/CHANGELOG.md",
    "MEDT/4xHITS-MEDT-Nodejs-Exoplanets/node_modules/uri-js/README.md",
    "MEDT/4xHITS-MEDT-Nodejs-Exoplanets/node_modules/swagger-ui-dist/favicon-16x16.png",
    "MEDT/4xHITS-MEDT-Nodejs-Exoplanets/node_modules/swagger-ui-dist/favicon-32x32.png",
    "Attachments/katholischeSozial.svg",
    "Attachments/WhatsApp Bild 2023-12-04 um 10.45.28_6e4d49c0.jpg",
    "Attachments/Gasig.jpg",
    "Attachments/Pasted image 20230915115957.png",
    "Attachments/Pasted image 20230926161135.png",
    "Attachments/Pasted image 20231123100821.png",
    "NWT/MitM.canvas",
    "Untitled-xmg-maz.canvas",
    "Untitled(2).canvas"
  ]
}